Decoder/decoder.v
module decoder2 (input wire sel,en, output wire [1:0] out);

    assign out[0] =en&(~sel); 
    assign out[1] =sel&en; 

endmodule

module decoder4 (input wire [1:0] sel, input wire en, output wire [3:0] out);
    wire [1:0] dOut;

    decoder2 d1(sel[1], en, dOut);

    decoder2 d2(sel[0], dOut[0], out[1:0]);
    decoder2 d3(sel[0], dOut[1], out[3:2]);
endmodule

module decoder8 (input wire [2:0] sel, input wire en, output wire [7:0] out);
    wire [1:0] dOut;

    decoder2 d1(sel[2], en, dOut);

    decoder4 d2(sel[1:0],dOut[0],out[3:0]);
    decoder4 d3(sel[1:0],dOut[1],out[7:4]);

     
endmodule

Decoder/decoder_TB.v
`include "decoder.v"


module decTest();

   reg [2:0] sel;
   reg enable;
   wire [7:0] out;


    decoder8 a1(sel, enable, out);

    initial begin
        $dumpfile("dump.vcd");
        $dumpvars(0, decTest);
    end

    initial begin
        $monitor("%b -(%b)-> %b",enable,sel,out);

        sel = 3'b000;
        enable = 1;
        #10;
        sel = 3'b001;
        enable = 1;
        #10;
        sel = 3'b010;
        enable = 1;
        #10;
        sel = 3'b011;
        enable = 1;
        #10;

        sel = 3'b100;
        enable = 1;
        #10;
        sel = 3'b101;
        enable = 1;
        #10;
        sel = 3'b110;
        enable = 1;
        #10;
        sel = 3'b111;
        enable = 1;
        #10;

    
       
            


    end


    

endmodule

Decoder/dump.vcd
$date
	Thu Sep 29 13:44:24 2022
$end
$version
	Icarus Verilog
$end
$timescale
	1s
$end
$scope module decTest $end
$var wire 8 ! out [7:0] $end
$var reg 1 " enable $end
$var reg 3 # sel [2:0] $end
$scope module a1 $end
$var wire 1 " en $end
$var wire 3 $ sel [2:0] $end
$var wire 8 % out [7:0] $end
$var wire 2 & dOut [1:0] $end
$scope module d1 $end
$var wire 1 " en $end
$var wire 1 ' sel $end
$var wire 2 ( out [1:0] $end
$upscope $end
$scope module d2 $end
$var wire 1 ) en $end
$var wire 2 * sel [1:0] $end
$var wire 4 + out [3:0] $end
$var wire 2 , dOut [1:0] $end
$scope module d1 $end
$var wire 1 ) en $end
$var wire 1 - sel $end
$var wire 2 . out [1:0] $end
$upscope $end
$scope module d2 $end
$var wire 1 / en $end
$var wire 1 0 sel $end
$var wire 2 1 out [1:0] $end
$upscope $end
$scope module d3 $end
$var wire 1 2 en $end
$var wire 1 3 sel $end
$var wire 2 4 out [1:0] $end
$upscope $end
$upscope $end
$scope module d3 $end
$var wire 1 5 en $end
$var wire 2 6 sel [1:0] $end
$var wire 4 7 out [3:0] $end
$var wire 2 8 dOut [1:0] $end
$scope module d1 $end
$var wire 1 5 en $end
$var wire 1 9 sel $end
$var wire 2 : out [1:0] $end
$upscope $end
$scope module d2 $end
$var wire 1 ; en $end
$var wire 1 < sel $end
$var wire 2 = out [1:0] $end
$upscope $end
$scope module d3 $end
$var wire 1 > en $end
$var wire 1 ? sel $end
$var wire 2 @ out [1:0] $end
$upscope $end
$upscope $end
$upscope $end
$upscope $end
$enddefinitions $end
$comment Show the parameter values. $end
$dumpall
$end
#0
$dumpvars
b0 @
0?
0>
b0 =
0<
0;
b0 :
09
b0 8
b0 7
b0 6
05
b0 4
03
02
b1 1
00
1/
b1 .
0-
b1 ,
b1 +
b0 *
1)
b1 (
0'
b1 &
b1 %
b0 $
b0 #
1"
b1 !
$end
#10
b10 !
b10 %
b10 +
b10 1
10
13
1<
1?
b1 *
b1 6
b1 #
b1 $
#20
0/
b1 4
12
b10 ,
b10 .
b100 !
b100 %
b100 +
b0 1
1-
00
03
19
0<
0?
b10 *
b10 6
b10 #
b10 $
#30
b1000 !
b1000 %
b1000 +
b10 4
10
13
1<
1?
b11 *
b11 6
b11 #
b11 $
#40
b0 1
b1 7
b1 =
0/
1;
0)
02
b1 8
b1 :
15
b0 ,
b0 .
b10000 !
b10000 %
b0 +
b0 4
b10 &
b10 (
0-
00
03
09
0<
0?
1'
b0 *
b0 6
b100 #
b100 $
#50
b100000 !
b100000 %
b10 7
b10 =
10
13
1<
1?
b1 *
b1 6
b101 #
b101 $
#60
0;
b1 @
1>
b10 8
b10 :
b1000000 !
b1000000 %
b100 7
b0 =
1-
00
03
19
0<
0?
b10 *
b10 6
b110 #
b110 $
#70
b10000000 !
b10000000 %
b1000 7
b10 @
10
13
1<
1?
b11 *
b11 6
b111 #
b111 $
